{
    "_id": "38000347|None",
    "id": "38000347",
    "infons": {},
    "passages": [
        {
            "infons": {
                "journal": "Stem Cell Res;2023Nov21; 73 103257. doi:10.1016/j.scr.2023.103257",
                "year": "2023",
                "type": "title",
                "authors": "Harancher MR, Sukhwani M, Castro CA, Hsieh MH, Orwig KE, "
            },
            "offset": 0,
            "text": "Generation of two isogenic sickle cell disease induced pluripotent stem cell lines from testicular fibroblasts.",
            "sentences": [],
            "annotations": [
                {
                    "id": "1",
                    "infons": {
                        "identifier": "MESH:D000755",
                        "type": "Disease",
                        "valid": true,
                        "normalized": [
                            "D000755"
                        ],
                        "database": "ncbi_mesh",
                        "normalized_id": "D000755",
                        "biotype": "disease",
                        "name": "Anemia Sickle Cell",
                        "accession": "@DISEASE_Anemia_Sickle_Cell"
                    },
                    "text": "sickle cell disease",
                    "locations": [
                        {
                            "offset": 27,
                            "length": 19
                        }
                    ]
                }
            ],
            "relations": []
        },
        {
            "infons": {
                "type": "abstract"
            },
            "offset": 112,
            "text": "Curative bone marrow transplantation (BMT) therapies for sickle cell disease (SCD) can cause infertility. The Fertility Preservation Program (FPP) in Pittsburgh cryopreserves testicular tissues for SCD patients prior to BMT in anticipation that those tissues can be thawed in the future and matured to produce sperm. Here, we generated and validated two isogenic patient-derived induced pluripotent stem cell (iPSC) lines from testicular biopsy fibroblasts of a 12-year-old SCD patient.",
            "sentences": [],
            "annotations": [
                {
                    "id": "7",
                    "infons": {
                        "identifier": "MESH:D000755",
                        "type": "Disease",
                        "valid": true,
                        "normalized": [
                            "D000755"
                        ],
                        "database": "ncbi_mesh",
                        "normalized_id": "D000755",
                        "biotype": "disease",
                        "name": "Anemia Sickle Cell",
                        "accession": "@DISEASE_Anemia_Sickle_Cell"
                    },
                    "text": "sickle cell disease",
                    "locations": [
                        {
                            "offset": 169,
                            "length": 19
                        }
                    ]
                },
                {
                    "id": "8",
                    "infons": {
                        "identifier": "MESH:D000755",
                        "type": "Disease",
                        "valid": true,
                        "normalized": [
                            "D000755"
                        ],
                        "database": "ncbi_mesh",
                        "normalized_id": "D000755",
                        "biotype": "disease",
                        "name": "Anemia Sickle Cell",
                        "accession": "@DISEASE_Anemia_Sickle_Cell"
                    },
                    "text": "SCD",
                    "locations": [
                        {
                            "offset": 190,
                            "length": 3
                        }
                    ]
                },
                {
                    "id": "9",
                    "infons": {
                        "identifier": "MESH:D007246",
                        "type": "Disease",
                        "valid": true,
                        "normalized": [
                            "D007246"
                        ],
                        "database": "ncbi_mesh",
                        "normalized_id": "D007246",
                        "biotype": "disease",
                        "name": "Infertility",
                        "accession": "@DISEASE_Infertility"
                    },
                    "text": "infertility",
                    "locations": [
                        {
                            "offset": 205,
                            "length": 11
                        }
                    ]
                },
                {
                    "id": "10",
                    "infons": {
                        "identifier": "MESH:D000755",
                        "type": "Disease",
                        "valid": true,
                        "normalized": [
                            "D000755"
                        ],
                        "database": "ncbi_mesh",
                        "normalized_id": "D000755",
                        "biotype": "disease",
                        "name": "Anemia Sickle Cell",
                        "accession": "@DISEASE_Anemia_Sickle_Cell"
                    },
                    "text": "SCD",
                    "locations": [
                        {
                            "offset": 310,
                            "length": 3
                        }
                    ]
                },
                {
                    "id": "11",
                    "infons": {
                        "identifier": "MESH:D000755",
                        "type": "Disease",
                        "valid": true,
                        "normalized": [
                            "D000755"
                        ],
                        "database": "ncbi_mesh",
                        "normalized_id": "D000755",
                        "biotype": "disease",
                        "name": "Anemia Sickle Cell",
                        "accession": "@DISEASE_Anemia_Sickle_Cell"
                    },
                    "text": "SCD",
                    "locations": [
                        {
                            "offset": 586,
                            "length": 3
                        }
                    ]
                }
            ],
            "relations": []
        }
    ],
    "relations": [],
    "pmid": 38000347,
    "pmcid": null,
    "meta": {},
    "date": "2023-12-01T00:00:00Z",
    "journal": "Stem Cell Res",
    "authors": [
        "Harancher MR",
        "Sukhwani M",
        "Castro CA",
        "Hsieh MH",
        "Orwig KE"
    ],
    "relations_display": []
}